MANIFEST.in
script
setup.py
bibtex_project/__init__.py
bibtex_project/controller.py
bibtex_project/model.py
bibtex_project/view.py
bibtex_project.egg-info/PKG-INFO
bibtex_project.egg-info/SOURCES.txt
bibtex_project.egg-info/dependency_links.txt
bibtex_project.egg-info/not-zip-safe
bibtex_project.egg-info/requires.txt
bibtex_project.egg-info/top_level.txt
test/test_controller.py
test/test_model.py
test/test_view.py